odoo/addons/pos_refund/README.rst
odoo/addons/pos_refund/__init__.py
odoo/addons/pos_refund/__manifest__.py
odoo/addons/pos_refund/i18n/es.po
odoo/addons/pos_refund/models/__init__.py
odoo/addons/pos_refund/models/pos_order.py
odoo/addons/pos_refund/models/pos_order_line.py
odoo/addons/pos_refund/models/stock_production_lot.py
odoo/addons/pos_refund/static/description/icon.png
odoo/addons/pos_refund/static/src/js/TicketScreen.js
odoo/addons/pos_refund/static/src/js/models.js
odoo/addons/pos_refund/static/src/js/Screens/ProductScreen/PosRefundScreen.js
odoo/addons/pos_refund/static/src/js/Screens/ProductScreen/RefundOrderDetails.js
odoo/addons/pos_refund/static/src/js/Screens/ProductScreen/RefundOrderLine.js
odoo/addons/pos_refund/static/src/js/Screens/ProductScreen/ControlButtons/PosRefundButton.js
odoo/addons/pos_refund/static/src/xml/PosRefundButton.xml
odoo/addons/pos_refund/static/src/xml/PosRefundScreen.xml
odoo/addons/pos_refund/static/src/xml/RefundOrderDetails.xml
odoo/addons/pos_refund/static/src/xml/RefundOrderLine.xml
odoo/addons/pos_refund/static/src/xml/TicketScreen.xml
odoo/addons/pos_refund/views/assets.xml
odoo/addons/pos_refund/views/pos_order_view.xml
odoo14_addon_pos_refund-14.0.1.0.0.dist-info/METADATA
odoo14_addon_pos_refund-14.0.1.0.0.dist-info/WHEEL
odoo14_addon_pos_refund-14.0.1.0.0.dist-info/top_level.txt
odoo14_addon_pos_refund-14.0.1.0.0.dist-info/RECORD
